MANIFEST.in
README.md
setup.py
./pythonhuecontrol/__init__.py
./pythonhuecontrol/v1/__init__.py
./pythonhuecontrol/v1/bridge/__init__.py
./pythonhuecontrol/v1/capabilities/__init__.py
./pythonhuecontrol/v1/configuration/__init__.py
./pythonhuecontrol/v1/group/__init__.py
./pythonhuecontrol/v1/light/__init__.py
./pythonhuecontrol/v1/resourcelinks/__init__.py
./pythonhuecontrol/v1/rule/__init__.py
./pythonhuecontrol/v1/scene/__init__.py
./pythonhuecontrol/v1/schedule/__init__.py
./pythonhuecontrol/v1/sensor/__init__.py
./pythonhuecontrol/v2/__init__.py
PythonHueControl.egg-info/PKG-INFO
PythonHueControl.egg-info/SOURCES.txt
PythonHueControl.egg-info/dependency_links.txt
PythonHueControl.egg-info/top_level.txt
pythonhuecontrol/__init__.py
pythonhuecontrol/v1/__init__.py
pythonhuecontrol/v1/bridge/__init__.py
pythonhuecontrol/v1/capabilities/__init__.py
pythonhuecontrol/v1/configuration/__init__.py
pythonhuecontrol/v1/group/__init__.py
pythonhuecontrol/v1/light/__init__.py
pythonhuecontrol/v1/resourcelinks/__init__.py
pythonhuecontrol/v1/rule/__init__.py
pythonhuecontrol/v1/scene/__init__.py
pythonhuecontrol/v1/schedule/__init__.py
pythonhuecontrol/v1/sensor/__init__.py
pythonhuecontrol/v2/__init__.py