Metadata-Version: 2.1
Name: PythonHueControl
Version: 0.4.2
Summary: Feature Rich Python API for Hue V1 and V2
Home-page: https://github.com/elnkosc/PythonHueControl
Author: Koen
Author-email: koen@schilders.org
License: GPL
Keywords: Hue,Python,API,Philips,Signify,Light,Sensor,IoT,Home Automation,Domotica
Platform: UNKNOWN
